Chamaeleo/__init__.py
Chamaeleo/data/binaries/DNA Fountain Input Files.tar.gz
Chamaeleo/data/binaries/Microsoft Winmine.exe
Chamaeleo/data/books/A Tale of Two Cities.pdf
Chamaeleo/data/books/The Wandering Earth.pdf
Chamaeleo/data/musics/For Elise.wma
Chamaeleo/data/musics/Summer.mp3
Chamaeleo/data/pictures/Mona Lisa.jpg
Chamaeleo/data/pictures/United Nations Flag.bmp
Chamaeleo/data/videos/Exiting the Factory.flv
Chamaeleo/data/videos/I have a Dream.mp4
Chamaeleo/examples/__init__.py
Chamaeleo/examples/demo_case_basic_feature.py
Chamaeleo/examples/demo_case_best_choice.py
Chamaeleo/examples/demo_case_combined_transcode.py
Chamaeleo/examples/demo_case_individual_transcode.py
Chamaeleo/examples/demo_case_robustness.py
Chamaeleo/examples/demo_case_transcode.py
Chamaeleo/examples/log_files/robustness.logs
Chamaeleo/examples/log_files/seq_features.logs
Chamaeleo/methods/__init__.py
Chamaeleo/methods/default.py
Chamaeleo/methods/ecc.py
Chamaeleo/methods/fixed.py
Chamaeleo/methods/flowed.py
Chamaeleo/methods/inherent.py
Chamaeleo/utils/__init__.py
Chamaeleo/utils/data_handle.py
Chamaeleo/utils/indexer.py
Chamaeleo/utils/monitor.py
Chamaeleo/utils/pipelines.py
Chamaeleo/utils/screen.py
Chamaeleo-1.34.dist-info/LICENSE
Chamaeleo-1.34.dist-info/METADATA
Chamaeleo-1.34.dist-info/WHEEL
Chamaeleo-1.34.dist-info/top_level.txt
Chamaeleo-1.34.dist-info/RECORD
